pytfsclient/__init__.py
pytfsclient/http_client.py
pytfsclient/tfs_client.py
pytfsclient/tfs_client_factory.py
pytfsclient/tfs_project_client.py
pytfsclient/tfs_project_model.py
pytfsclient/tfs_wiql_model.py
pytfsclient/tfs_workitem_client.py
pytfsclient/tfs_workitem_model.py
pytfsclient/tfs_workitem_relation_model.py
pytfsclient-0.9.4.dist-info/LICENSE.txt
pytfsclient-0.9.4.dist-info/METADATA
pytfsclient-0.9.4.dist-info/WHEEL
pytfsclient-0.9.4.dist-info/top_level.txt
pytfsclient-0.9.4.dist-info/RECORD
